mkdocs_glightbox/__init__.py
mkdocs_glightbox/plugin.py
mkdocs_glightbox/glightbox/LICENSE.md
mkdocs_glightbox/glightbox/glightbox.min.css
mkdocs_glightbox/glightbox/glightbox.min.js
mkdocs_glightbox-0.5.1.dist-info/METADATA
mkdocs_glightbox-0.5.1.dist-info/WHEEL
mkdocs_glightbox-0.5.1.dist-info/entry_points.txt
mkdocs_glightbox-0.5.1.dist-info/licenses/LICENSE
mkdocs_glightbox-0.5.1.dist-info/RECORD
