Metadata-Version: 2.4
Name: mkdocs-glightbox
Version: 0.5.1
Summary: MkDocs plugin supports image lightbox with GLightbox.
Project-URL: Homepage, https://blueswen.github.io/mkdocs-glightbox/
Project-URL: Source, https://github.com/blueswen/mkdocs-glightbox
Project-URL: Issues, https://github.com/blueswen/mkdocs-glightbox/issues
Project-URL: History, https://github.com/blueswen/mkdocs-glightbox/blob/main/CHANGELOG
Author-email: Blueswen <blueswen.tw@gmail.com>
License-Expression: MIT
License-File: LICENSE
Keywords: glightbox,mkdocs,plugin
Classifier: Development Status :: 5 - Production/Stable
Classifier: Environment :: Console
Classifier: Environment :: Web Environment
Classifier: Intended Audience :: Developers
Classifier: License :: OSI Approved :: MIT License
Classifier: Operating System :: OS Independent
Classifier: Programming Language :: Python
Classifier: Programming Language :: Python :: 3
Classifier: Programming Language :: Python :: 3 :: Only
Classifier: Programming Language :: Python :: 3.8
Classifier: Programming Language :: Python :: 3.9
Classifier: Programming Language :: Python :: 3.10
Classifier: Programming Language :: Python :: 3.11
Classifier: Programming Language :: Python :: 3.12
Classifier: Topic :: Documentation
Classifier: Topic :: Text Processing
Requires-Python: >=3.8
Requires-Dist: selectolax==0.3.29
